pyxll_holoviz/__init__.py
pyxll_holoviz/hvplot_bridge.py
pyxll_holoviz/panel_bridge.py
pyxll_holoviz/pyxll.py
pyxll_holoviz/udfs.py
pyxll_holoviz/ribbon/__init__.py
pyxll_holoviz/ribbon/actions.py
pyxll_holoviz/ribbon/hvplot.png
pyxll_holoviz/ribbon/ribbon.xml
pyxll_holoviz-1.0.0.dist-info/LICENSE.md
pyxll_holoviz-1.0.0.dist-info/METADATA
pyxll_holoviz-1.0.0.dist-info/WHEEL
pyxll_holoviz-1.0.0.dist-info/entry_points.txt
pyxll_holoviz-1.0.0.dist-info/top_level.txt
pyxll_holoviz-1.0.0.dist-info/RECORD
