Metadata-Version: 2.1
Name: pyxll-holoviz
Version: 1.0.0
Summary: PyXLL extension for Holoviz charts and panels
Author-email: Tony Roberts <tony@pyxll.com>
License: # MIT License
Project-URL: Homepage, https://github.com/pyxll/pyxll-holoviz
Project-URL: Repository, https://github.com/pyxll/pyxll-holoviz.git
Project-URL: Issues, https://github.com/pyxll/pyxll-holoviz/issues
Classifier: Programming Language :: Python :: 3
Classifier: License :: OSI Approved :: MIT License
Classifier: Operating System :: Microsoft :: Windows
License-File: LICENSE.md
Requires-Dist: pyxll>=5.9.0
Requires-Dist: hvplot
Requires-Dist: holoviews
Requires-Dist: panel
Requires-Dist: tornado
Requires-Dist: pywin32
